[{"id":0,"name":"Cole Warren","birthYear":"1980","city":"Tilapu"},{"id":1,"name":"Francis Goodman","birthYear":"2000","city":"Lotzarkov"},{"id":2,"name":"Ian Vega","birthYear":"1943","city":"Lejrupov"},{"id":3,"name":"Dominic Cobb","birthYear":"1947","city":"Fafeka"},{"id":4,"name":"Jesse Richards","birthYear":"1970","city":"Ladaboud"},{"id":5,"name":"Samuel Wallace","birthYear":"1974","city":"Wubedipo"},{"id":6,"name":"Marion Flores","birthYear":"1943","city":"Silbudmoj"},{"id":7,"name":"Mable Cook","birthYear":"1976","city":"Fouguopa"},{"id":8,"name":"Maude Thornton","birthYear":"1951","city":"Tefaduw"},{"id":9,"name":"Jayden Floyd","birthYear":"1994","city":"Epefabak"},{"id":10,"name":"Bill Nash","birthYear":"1948","city":"Agenumik"},{"id":11,"name":"Sean Graham","birthYear":"1975","city":"Kaezofed"},{"id":12,"name":"Carlos Rivera","birthYear":"1963","city":"Ikehebipi"},{"id":13,"name":"Katharine Chandler","birthYear":"1943","city":"Helengo"},{"id":14,"name":"Tony Mann","birthYear":"1965","city":"Esdazeg"},{"id":15,"name":"Oscar Williamson","birthYear":"1963","city":"Fokojif"},{"id":16,"name":"Minerva Barnes","birthYear":"1964","city":"Fotewzi"},{"id":17,"name":"Ann Porter","birthYear":"1976","city":"Jondoron"},{"id":18,"name":"Leroy Marsh","birthYear":"1995","city":"Lindovico"},{"id":19,"name":"Derek Hammond","birthYear":"1974","city":"Zemimim"},{"id":20,"name":"Della Davis","birthYear":"1975","city":"Emaveoz"},{"id":21,"name":"Jason Owen","birthYear":"1979","city":"Conogsid"},{"id":22,"name":"Marguerite Wallace","birthYear":"1995","city":"Tajcuba"},{"id":23,"name":"Leon Doyle","birthYear":"1979","city":"Vasupgi"},{"id":24,"name":"Alberta Baker","birthYear":"1982","city":"Egbokohe"},{"id":25,"name":"Lottie Powell","birthYear":"1983","city":"Afrotsor"},{"id":26,"name":"Harriet Alexander","birthYear":"1966","city":"Suihekot"},{"id":27,"name":"Adam Tate","birthYear":"1963","city":"Lepogve"},{"id":28,"name":"Rhoda Hanson","birthYear":"1934","city":"Defimiom"},{"id":29,"name":"Marguerite Greene","birthYear":"1975","city":"Avahere"},{"id":30,"name":"Joshua Edwards","birthYear":"1963","city":"Ahetawir"},{"id":31,"name":"Adeline Fitzgerald","birthYear":"1987","city":"Sufohob"},{"id":32,"name":"May Sparks","birthYear":"1983","city":"Kenemo"},{"id":33,"name":"Scott Powell","birthYear":"1934","city":"Ropdecbu"},{"id":34,"name":"Andre Page","birthYear":"1979","city":"Itkasur"},{"id":35,"name":"Katherine Butler","birthYear":"1979","city":"Gumsafsad"},{"id":36,"name":"Daniel Fernandez","birthYear":"1939","city":"Gumeniw"},{"id":37,"name":"Luis Reyes","birthYear":"1987","city":"Negasfun"},{"id":38,"name":"Vernon Curtis","birthYear":"1964","city":"Uphemar"},{"id":39,"name":"Bess Jordan","birthYear":"1984","city":"Wihefbu"},{"id":40,"name":"Alfred Davidson","birthYear":"1988","city":"Foubases"},{"id":41,"name":"Ernest Gibbs","birthYear":"1946","city":"Vedfaduk"},{"id":42,"name":"Minnie Bowen","birthYear":"1999","city":"Ufocizvif"},{"id":43,"name":"Randall Norris","birthYear":"1964","city":"Avjaveli"},{"id":44,"name":"Earl Young","birthYear":"1947","city":"Deglinse"},{"id":45,"name":"Elsie Norris","birthYear":"1963","city":"Adepnus"},{"id":46,"name":"Phoebe Clayton","birthYear":"1971","city":"Liwsotlaf"},{"id":47,"name":"Steve Lucas","birthYear":"1975","city":"Uhalba"},{"id":48,"name":"Katie Atkins","birthYear":"1984","city":"Lebrewe"},{"id":49,"name":"Cynthia Sims","birthYear":"1963","city":"Fodour"},{"id":50,"name":"Alma Fernandez","birthYear":"1954","city":"Nugcias"},{"id":51,"name":"Erik Ballard","birthYear":"1998","city":"Raovuzi"},{"id":52,"name":"Flora Bates","birthYear":"1946","city":"Jurohu"},{"id":53,"name":"Gabriel Houston","birthYear":"1932","city":"Isnicaj"},{"id":54,"name":"Eugene Thornton","birthYear":"1956","city":"Lemovluk"},{"id":55,"name":"Louis McKinney","birthYear":"1963","city":"Daavainu"},{"id":56,"name":"Alvin Brown","birthYear":"1946","city":"Solgivsi"},{"id":57,"name":"Calvin Flores","birthYear":"1948","city":"Taafac"},{"id":58,"name":"Lina Taylor","birthYear":"2001","city":"Zifobu"},{"id":59,"name":"Floyd Moody","birthYear":"1995","city":"Loczuski"},{"id":60,"name":"Hattie Bass","birthYear":"1978","city":"Zakodop"},{"id":61,"name":"Winnie Jenkins","birthYear":"1957","city":"Gadonrap"},{"id":62,"name":"Nelle Miles","birthYear":"1943","city":"Keevog"},{"id":63,"name":"Danny Barber","birthYear":"1997","city":"Kususem"},{"id":64,"name":"Philip Burke","birthYear":"1967","city":"Debzepig"},{"id":65,"name":"Nancy Erickson","birthYear":"1953","city":"Luewaro"},{"id":66,"name":"Maud Hampton","birthYear":"1961","city":"Upajiseh"},{"id":67,"name":"Mable Morgan","birthYear":"1968","city":"Urneic"},{"id":68,"name":"Nannie Reeves","birthYear":"1987","city":"Nawdekoma"},{"id":69,"name":"Gene Hernandez","birthYear":"1966","city":"Nedwogpoz"},{"id":70,"name":"Minerva Lee","birthYear":"1987","city":"Zinolmaj"},{"id":71,"name":"Norman Morris","birthYear":"1952","city":"Hosnawe"},{"id":72,"name":"Sam Paul","birthYear":"1984","city":"Apgenu"},{"id":73,"name":"Abbie Burke","birthYear":"2000","city":"Gajgolkap"},{"id":74,"name":"Eric Pena","birthYear":"1971","city":"Fecsunan"},{"id":75,"name":"Walter Obrien","birthYear":"1948","city":"Penuavu"},{"id":76,"name":"Jack Graves","birthYear":"1983","city":"Hanuzupi"},{"id":77,"name":"Lloyd Silva","birthYear":"1976","city":"Diremeus"},{"id":78,"name":"Cecelia Oliver","birthYear":"1951","city":"Hacuiti"},{"id":79,"name":"Frederick Gutierrez","birthYear":"1994","city":"Tadsacun"},{"id":80,"name":"Frederick Drake","birthYear":"1938","city":"Emabaffi"},{"id":81,"name":"Myra Gill","birthYear":"1966","city":"Muebuleg"},{"id":82,"name":"Sara Carter","birthYear":"1943","city":"Unliguc"},{"id":83,"name":"Chase Parker","birthYear":"1988","city":"Vortihaw"},{"id":84,"name":"Lucille Jefferson","birthYear":"1987","city":"Kudnijute"},{"id":85,"name":"Milton Waters","birthYear":"1939","city":"Ipoduhi"},{"id":86,"name":"Ella Hall","birthYear":"1985","city":"Kufunaci"},{"id":87,"name":"Josie Sparks","birthYear":"1962","city":"Gafofun"},{"id":88,"name":"Anne Little","birthYear":"1982","city":"Lovinjon"},{"id":89,"name":"Elsie Fox","birthYear":"1955","city":"Woakomiw"},{"id":90,"name":"Jay Higgins","birthYear":"1958","city":"Jadvade"},{"id":91,"name":"Maude Stephens","birthYear":"1995","city":"Velsebu"},{"id":92,"name":"Blanche Oliver","birthYear":"1965","city":"Usarefi"},{"id":93,"name":"Craig Brady","birthYear":"1981","city":"Kehupo"},{"id":94,"name":"Darrell Bush","birthYear":"1989","city":"Cuwmuzic"},{"id":95,"name":"Nancy Porter","birthYear":"1995","city":"Zivlimgat"},{"id":96,"name":"Betty Peterson","birthYear":"1977","city":"Utrajut"},{"id":97,"name":"Landon Abbott","birthYear":"1989","city":"Admunake"},{"id":98,"name":"Landon Burgess","birthYear":"2001","city":"Suhjopgi"},{"id":99,"name":"Micheal Rios","birthYear":"1969","city":"Owjecunu"},{"id":100,"name":"Dale Allen","birthYear":"1980","city":"Rofidco"},{"id":101,"name":"Franklin Gilbert","birthYear":"1985","city":"Jimtubu"},{"id":102,"name":"Edith Sullivan","birthYear":"1946","city":"Sulutitu"},{"id":103,"name":"Alice Swanson","birthYear":"1947","city":"Luggozze"},{"id":104,"name":"Nicholas McCoy","birthYear":"1980","city":"Faguces"},{"id":105,"name":"Craig Berry","birthYear":"1984","city":"Bazwipu"},{"id":106,"name":"Rhoda Jennings","birthYear":"1980","city":"Vousuzuc"},{"id":107,"name":"Cordelia Vaughn","birthYear":"1951","city":"Hapimfu"},{"id":108,"name":"Floyd Gill","birthYear":"1984","city":"Onehale"},{"id":109,"name":"Viola Valdez","birthYear":"1992","city":"Guvune"},{"id":110,"name":"Tyler Hammond","birthYear":"1955","city":"Ojtahod"},{"id":111,"name":"Melvin Clark","birthYear":"1999","city":"Imheda"},{"id":112,"name":"Harriet Clarke","birthYear":"1944","city":"Wuliknok"},{"id":113,"name":"Russell Larson","birthYear":"1989","city":"Migekuko"},{"id":114,"name":"Gordon Tate","birthYear":"1988","city":"Zadagkob"},{"id":115,"name":"Pauline Porter","birthYear":"1932","city":"Ovrofod"},{"id":116,"name":"Esther Dunn","birthYear":"1934","city":"Hemiawi"},{"id":117,"name":"Erik Ramsey","birthYear":"1943","city":"Gavoata"},{"id":118,"name":"Louisa Kennedy","birthYear":"1975","city":"Lolrahida"},{"id":119,"name":"Vernon Farmer","birthYear":"1930","city":"Honzajtap"},{"id":120,"name":"Steve Dawson","birthYear":"1959","city":"Focusumaf"},{"id":121,"name":"Eleanor Hogan","birthYear":"1969","city":"Orozebsud"},{"id":122,"name":"Randy Fleming","birthYear":"1934","city":"Wisgopen"},{"id":123,"name":"Addie Romero","birthYear":"1980","city":"Jucduru"},{"id":124,"name":"Cole Jenkins","birthYear":"1957","city":"Viudago"},{"id":125,"name":"Shane Williams","birthYear":"1965","city":"Ucitauz"},{"id":126,"name":"Wayne Weaver","birthYear":"2000","city":"Mukcajiz"},{"id":127,"name":"Dollie Franklin","birthYear":"1981","city":"Ivhohe"},{"id":128,"name":"Robert Price","birthYear":"1995","city":"Acafezrap"},{"id":129,"name":"Mathilda Watson","birthYear":"1985","city":"Zablaltus"},{"id":130,"name":"Francis Mullins","birthYear":"1941","city":"Gefciji"},{"id":131,"name":"Edna Reed","birthYear":"1993","city":"Rodajoni"},{"id":132,"name":"Connor Harvey","birthYear":"1933","city":"Nuesgo"},{"id":133,"name":"Jason Martinez","birthYear":"1948","city":"Buhiva"},{"id":134,"name":"Cynthia Munoz","birthYear":"1997","city":"Rupafi"},{"id":135,"name":"Sadie Hardy","birthYear":"1948","city":"Epkifus"},{"id":136,"name":"Kyle Pittman","birthYear":"1984","city":"Gozreew"},{"id":137,"name":"Caroline Gregory","birthYear":"1973","city":"Adehedla"},{"id":138,"name":"Edward Cummings","birthYear":"1946","city":"Mowipve"},{"id":139,"name":"Ernest Estrada","birthYear":"1978","city":"Karozso"},{"id":140,"name":"Todd Carson","birthYear":"1993","city":"Jefalu"},{"id":141,"name":"Dustin Walton","birthYear":"1983","city":"Sagidume"},{"id":142,"name":"Randall Long","birthYear":"1955","city":"Kurirha"},{"id":143,"name":"Alex Barker","birthYear":"1943","city":"Jizali"},{"id":144,"name":"Nannie Ferguson","birthYear":"1952","city":"Jentiohu"},{"id":145,"name":"Rebecca Hammond","birthYear":"1930","city":"Ocihijgit"},{"id":146,"name":"Theresa Mason","birthYear":"1998","city":"Mahelu"},{"id":147,"name":"Garrett Houston","birthYear":"1939","city":"Zekwijad"},{"id":148,"name":"Leroy Moss","birthYear":"1956","city":"Rurefluw"},{"id":149,"name":"Calvin Cain","birthYear":"1947","city":"Veezige"}]
